aupyom/__init__.py
aupyom/dummy_stream.py
aupyom/sampler.py
aupyom/sound.py
aupyom/util.py
aupyom/version.py
aupyom/example_data/Tom's Dinner - Full.wav
aupyom/example_data/Tom's Dinner.wav
aupyom-0.1.0.dist-info/DESCRIPTION.rst
aupyom-0.1.0.dist-info/METADATA
aupyom-0.1.0.dist-info/RECORD
aupyom-0.1.0.dist-info/WHEEL
aupyom-0.1.0.dist-info/metadata.json
aupyom-0.1.0.dist-info/top_level.txt
